README.md
setup.py
mod_net.egg-info/PKG-INFO
mod_net.egg-info/SOURCES.txt
mod_net.egg-info/dependency_links.txt
mod_net.egg-info/entry_points.txt
mod_net.egg-info/requires.txt
mod_net.egg-info/top_level.txt
modnet/__init__.py
modnet/analysis.py
modnet/logic.py
modnet/tests/__init__.py
modnet/tests/test_logic_01.py