Metadata-Version: 1.0
Name: mod-net
Version: 0
Summary: Make SET and SEU fault injections in hierarchical verilog netlists
Home-page: UNKNOWN
Author: UNKNOWN
Author-email: UNKNOWN
License: UNKNOWN
Platform: UNKNOWN
